{
    "nii_path":"../dataset/train",
    "npy_path":"../dataset/npy_data",
    "metadata_path":"./meta_data/spine_metadata.csv",
    "annotation_num":19,
    "annotation_list":[
        "S",
        "L5",
        "L4",
        "L3",
        "L2",
        "L1",
        "T12",
        "T11",
        "T10",
        "T9",
        "L5/S",
        "L4/L5",
        "L3/L4",
        "L2/L3",
        "L1/L2",
        "T12/L1",
        "T11/T12",
        "T10/T11",
        "T9/T10"
    ],
    "2d_data":{
        "save_path":"../dataset/2d_data",
        "crop":0,
        "shape":[512,512],
        "csv_path":"./static_files/spine.csv"
    },
    "mean_std":{
        "mean":239,
        "std":257
    }
}